toutiao.py
version.py
toutiao-0.0.2.dist-info/LICENSE.txt
toutiao-0.0.2.dist-info/METADATA
toutiao-0.0.2.dist-info/RECORD
toutiao-0.0.2.dist-info/WHEEL
toutiao-0.0.2.dist-info/entry_points.txt
toutiao-0.0.2.dist-info/top_level.txt
