Metadata-Version: 2.1
Name: toutiao
Version: 0.0.2
Summary: CLI tool for toutiao.io
Home-page: https://github.com/doukeshi/toutiao-cli
Author: Doukeshi
Author-email: doukeshi@users.noreply.github.com
License: MIT License
Requires-Dist: click
Requires-Dist: requests
Requires-Dist: beautifulsoup4
